vaultsandbox/__init__.py
vaultsandbox/client.py
vaultsandbox/constants.py
vaultsandbox/email.py
vaultsandbox/errors.py
vaultsandbox/inbox.py
vaultsandbox/py.typed
vaultsandbox/types.py
vaultsandbox/webhook.py
vaultsandbox/crypto/__init__.py
vaultsandbox/crypto/constants.py
vaultsandbox/crypto/decrypt.py
vaultsandbox/crypto/keypair.py
vaultsandbox/crypto/signature.py
vaultsandbox/crypto/utils.py
vaultsandbox/crypto/validation.py
vaultsandbox/http/__init__.py
vaultsandbox/http/api_client.py
vaultsandbox/http/base_client.py
vaultsandbox/http/chaos_client.py
vaultsandbox/http/email_client.py
vaultsandbox/http/inbox_client.py
vaultsandbox/http/webhook_client.py
vaultsandbox/strategies/__init__.py
vaultsandbox/strategies/delivery_strategy.py
vaultsandbox/strategies/polling_strategy.py
vaultsandbox/strategies/sse_strategy.py
vaultsandbox/utils/__init__.py
vaultsandbox/utils/datetime_utils.py
vaultsandbox/utils/email_utils.py
vaultsandbox/utils/sleep.py
vaultsandbox/utils/validation.py
vaultsandbox/utils/webhook_utils.py
vaultsandbox-0.9.2.dist-info/METADATA
vaultsandbox-0.9.2.dist-info/WHEEL
vaultsandbox-0.9.2.dist-info/licenses/LICENSE
vaultsandbox-0.9.2.dist-info/RECORD
