Metadata-Version: 2.4
Name: vaultsandbox
Version: 0.9.2
Summary: Python SDK for VaultSandbox - Secure, receive-only SMTP server for QA/testing with quantum-safe encryption
Project-URL: Homepage, https://vaultsandbox.com
Project-URL: Documentation, https://vaultsandbox.dev
Project-URL: Repository, https://github.com/vaultsandbox/client-python
Project-URL: Issues, https://github.com/vaultsandbox/client-python/issues
Project-URL: Discussions, https://github.com/vaultsandbox/gateway/discussions
Author-email: Antero <antero@vaultsandbox.com>
License-Expression: Apache-2.0
License-File: LICENSE
Keywords: email,encryption,kyber,ml-kem,qa,quantum-safe,smtp,testing
Classifier: Development Status :: 4 - Beta
Classifier: Intended Audience :: Developers
Classifier: License :: OSI Approved :: Apache Software License
Classifier: Operating System :: OS Independent
Classifier: Programming Language :: Python :: 3
Classifier: Programming Language :: Python :: 3.10
Classifier: Programming Language :: Python :: 3.11
Classifier: Programming Language :: Python :: 3.12
Classifier: Programming Language :: Python :: 3.13
Classifier: Topic :: Communications :: Email
Classifier: Topic :: Security :: Cryptography
Classifier: Topic :: Software Development :: Testing
Classifier: Typing :: Typed
Requires-Python: >=3.10
Requires-Dist: cryptography>=42.0.0
Requires-Dist: httpx-sse>=0.4.0
Requires-Dist: httpx>=0.27.0
Requires-Dist: pqcrypto>=0.3.4
Provides-Extra: dev
Requires-Dist: mypy>=1.8.0; extra == 'dev'
Requires-Dist: pytest-asyncio>=0.23.0; extra == 'dev'
Requires-Dist: pytest-cov>=4.1.0; extra == 'dev'
Requires-Dist: pytest-xdist>=3.5.0; extra == 'dev'
Requires-Dist: pytest>=8.0.0; extra == 'dev'
Requires-Dist: python-dotenv>=1.0.0; extra == 'dev'
Requires-Dist: ruff>=0.3.0; extra == 'dev'
